[
    {
        "id": 1773398683183,
        "data": "13/03/2026, 11:44:43",
        "pilota": "Pilota 1",
        "percorso": "Rally 1",
        "tipo": "Prova 1",
        "meteo": "Asciutto",
        "parziali": [
            {
                "tempo": "00:00.3",
                "ms": 319
            },
            {
                "tempo": "00:00.6",
                "ms": 609
            },
            {
                "tempo": "00:01.0",
                "ms": 971
            },
            {
                "tempo": "00:02.1",
                "ms": 2100
            }
        ]
    }
]